lazy_tailscale/__init__.py
lazy_tailscale/cli.py
lazy_tailscale/client/__init__.py
lazy_tailscale/client/async_client.py
lazy_tailscale/client/blocking_client.py
lazy_tailscale/client/exceptions.py
lazy_tailscale/client/resources/__init__.py
lazy_tailscale/client/resources/device.py
lazy_tailscale/core/__init__.py
lazy_tailscale/core/exceptions.py
lazy_tailscale/core/local_service.py
lazy_tailscale/core/protocols.py
lazy_tailscale/core/remote_service.py
lazy_tailscale/core/utils.py
lazy_tailscale/dependencies.py
lazy_tailscale/local_client/__init__.py
lazy_tailscale/local_client/client.py
lazy_tailscale/local_client/exceptions.py
lazy_tailscale/local_client/status.py
lazy_tailscale/ui/__init__.py
lazy_tailscale/ui/app.py
lazy_tailscale/ui/device_detail.py
lazy_tailscale/ui/device_list.py
lazy_tailscale/ui/exit_node_detai.py
lazy_tailscale/ui/exit_node_list.py
lazy_tailscale/ui/notification.py
lazy_tailscale/ui/online_indicator.py
lazy_tailscale/ui/os_logo.py
lazy_tailscale/ui/ssh_indicator.py
lazy_tailscale/ui/status_badge.py
lazy_tailscale/ui/style.tcss
lazy_tailscale/ui/utils.py
lazy_tailscale-0.2.1.dist-info/WHEEL
lazy_tailscale-0.2.1.dist-info/entry_points.txt
lazy_tailscale-0.2.1.dist-info/METADATA
lazy_tailscale-0.2.1.dist-info/RECORD
