Metadata-Version: 2.4
Name: lazy-tailscale
Version: 0.2.1
Summary: A textual user interface for interacting with Tailscale.
Author: Pascal Pfeiffer
License-Expression: MIT
Requires-Dist: aiohttp>=3.13.2
Requires-Dist: click>=8.3.0
Requires-Dist: httpx>=0.28.1
Requires-Dist: pydantic>=2.12.3
Requires-Dist: textual>=6.5.0
Requires-Python: >=3.10
